sphinxcontrib/__init__.py
sphinxcontrib/sqltable.py
sphinxcontrib.sqltable-2.1.1.dist-info/LICENSE
sphinxcontrib.sqltable-2.1.1.dist-info/METADATA
sphinxcontrib.sqltable-2.1.1.dist-info/WHEEL
sphinxcontrib.sqltable-2.1.1.dist-info/top_level.txt
sphinxcontrib.sqltable-2.1.1.dist-info/RECORD
