Metadata-Version: 2.1
Name: sphinxcontrib.sqltable
Version: 2.1.1
Summary: Sphinx extension for embedding database content in documents
Author-email: Doug Hellmann <doug@doughellmann.com>
Project-URL: homepage, https://sphinxcontrib-sqltable.readthedocs.io/en/latest/
Project-URL: repository, http://github.com/sphinx-contrib/sqltable
Classifier: Development Status :: 5 - Production/Stable
Classifier: Environment :: Console
Classifier: Environment :: Web Environment
Classifier: Intended Audience :: Developers
Classifier: License :: OSI Approved :: BSD License
Classifier: Operating System :: OS Independent
Classifier: Programming Language :: Python
Classifier: Programming Language :: Python :: 3.9
Classifier: Programming Language :: Python :: 3.10
Classifier: Programming Language :: Python :: 3.11
Classifier: Programming Language :: Python :: 3.12
Classifier: Topic :: Database
Classifier: Topic :: Documentation
Classifier: Topic :: Utilities
Requires-Python: >=3.9
License-File: LICENSE
Requires-Dist: Sphinx >=2.0.0
Requires-Dist: SQLAlchemy >=2.0
Provides-Extra: build
Requires-Dist: build ; extra == 'build'
Requires-Dist: twine ; extra == 'build'
Provides-Extra: docs
Requires-Dist: sphinx-rtd-theme ; extra == 'docs'
Requires-Dist: sphinx ; extra == 'docs'
Provides-Extra: linter
Requires-Dist: flake8 ; extra == 'linter'
Provides-Extra: test
Requires-Dist: pytest ; extra == 'test'
Requires-Dist: beautifulsoup4 ; extra == 'test'
